drive_cse_upload/__init__.py
drive_cse_upload/_cse_crypter.py
drive_cse_upload/_cse_crypter_test.py
drive_cse_upload/_cse_drive_client.py
drive_cse_upload/_cse_idp_client.py
drive_cse_upload/_cse_kacls_client.py
drive_cse_upload/_cse_kacls_client_test.py
drive_cse_upload/_cse_keyset_util.py
drive_cse_upload/_cse_util.py
drive_cse_upload/_cse_util_test.py
drive_cse_upload/cse_uploader.py
drive_cse_upload/example.py
drive_cse_upload-1.0.1.dist-info/METADATA
drive_cse_upload-1.0.1.dist-info/WHEEL
drive_cse_upload-1.0.1.dist-info/licenses/LICENSE
drive_cse_upload-1.0.1.dist-info/RECORD
