Metadata-Version: 2.4
Name: drive-cse-upload
Version: 1.0.1
Summary: Upload a file from local-host to Google Drive as a Client Side Encrypted (CSE) document
Project-URL: Repository, https://github.com/googleworkspace/drive-cse-upload
Author-email: Drive CSE Team <no-reply@google.com>
License: 
License-File: LICENSE
Classifier: Development Status :: 4 - Beta
Classifier: Intended Audience :: Developers
Classifier: License :: OSI Approved :: Apache Software License
Classifier: Operating System :: OS Independent
Classifier: Programming Language :: Python :: 3
Requires-Python: >=3.10.7
Requires-Dist: google-api-python-client
Requires-Dist: google-auth-httplib2
Requires-Dist: google-auth-oauthlib
Requires-Dist: tink>=1.10.0
